{"textures":[{"image":"27-0.webp","format":"RGBA8888","size":{"w":226,"h":426},"scale":1,"frames":[{"filename":"bodyBG","rotated":false,"trimmed":true,"sourceSize":{"w":224,"h":199},"spriteSourceSize":{"x":0,"y":0,"w":224,"h":199},"frame":{"x":1,"y":1,"w":224,"h":199}},{"filename":"bodyFG","rotated":false,"trimmed":true,"sourceSize":{"w":224,"h":199},"spriteSourceSize":{"x":7,"y":49,"w":193,"h":150},"frame":{"x":1,"y":202,"w":193,"h":150}},{"filename":"body","rotated":false,"trimmed":true,"sourceSize":{"w":224,"h":199},"spriteSourceSize":{"x":89,"y":49,"w":72,"h":71},"frame":{"x":1,"y":354,"w":72,"h":71}}]}],"meta":{"app":"https://www.codeandweb.com/texturepacker","version":"3.0","smartupdate":"$TexturePacker:SmartUpdate:f84ec4cb10b68bd3aa6b9b226f619052:1fe1de72dadf59c60d6d33ea5a77ad68:24c950237314d82b8c4952ea0d6caebb$"}}